redis_session/__init__.py
redis_session/flask_session.py
redis_session/model.py
redis_session/session.py
redis_session/tornado_session.py
redis_session-0.2.1.dist-info/METADATA
redis_session-0.2.1.dist-info/RECORD
redis_session-0.2.1.dist-info/WHEEL
redis_session-0.2.1.dist-info/top_level.txt
redis_session-0.2.1.dist-info/zip-safe
