Metadata-Version: 2.1
Name: redis_session
Version: 0.2.1
Summary: Simple session implementation for python3 web frameworks
Home-page: http://github.com/devfans/redis-session
Author: Stefan Liu
Author-email: stefanliu@outlook.com
License: MIT
Keywords: redis_session tornado web cookie session redis python
Platform: UNKNOWN
Classifier: License :: OSI Approved :: MIT License
Classifier: Topic :: Internet :: WWW/HTTP :: Session
Classifier: Programming Language :: Python :: 3
Classifier: Environment :: Web Environment
Classifier: Intended Audience :: Developers
Classifier: Operating System :: OS Independent
